self_documenting_f_string/__init__.py
self_documenting_f_string/f_string_rule.py
self_documenting_f_string-0.1.1.dist-info/METADATA
self_documenting_f_string-0.1.1.dist-info/WHEEL
self_documenting_f_string-0.1.1.dist-info/entry_points.txt
self_documenting_f_string-0.1.1.dist-info/top_level.txt
self_documenting_f_string-0.1.1.dist-info/RECORD
